odoo/addons/stock_picking_origin_reference_purchase/README.rst
odoo/addons/stock_picking_origin_reference_purchase/__init__.py
odoo/addons/stock_picking_origin_reference_purchase/__manifest__.py
odoo/addons/stock_picking_origin_reference_purchase/i18n/it.po
odoo/addons/stock_picking_origin_reference_purchase/i18n/stock_picking_origin_reference_purchase.pot
odoo/addons/stock_picking_origin_reference_purchase/models/__init__.py
odoo/addons/stock_picking_origin_reference_purchase/models/stock_picking.py
odoo/addons/stock_picking_origin_reference_purchase/readme/CONTRIBUTORS.md
odoo/addons/stock_picking_origin_reference_purchase/readme/DESCRIPTION.md
odoo/addons/stock_picking_origin_reference_purchase/static/description/icon.png
odoo/addons/stock_picking_origin_reference_purchase/static/description/index.html
odoo/addons/stock_picking_origin_reference_purchase/tests/__init__.py
odoo/addons/stock_picking_origin_reference_purchase/tests/test_stock_picking_origin_reference_purchase.py
odoo_addon_stock_picking_origin_reference_purchase-18.0.1.0.0.2.dist-info/METADATA
odoo_addon_stock_picking_origin_reference_purchase-18.0.1.0.0.2.dist-info/WHEEL
odoo_addon_stock_picking_origin_reference_purchase-18.0.1.0.0.2.dist-info/top_level.txt
odoo_addon_stock_picking_origin_reference_purchase-18.0.1.0.0.2.dist-info/RECORD
